{
  "seed": {
    "item": "atmospheric:kousa_sapling"
  },
  "categories": [
    "dirt"
  ],
  "growthTicks": 3600,
  "display": {
    "type": "block",
    "block": "atmospheric:kousa_sapling"
  },
  "results": [
    {
      "chance": 1.0,
      "output": {
        "item": "atmospheric:kousa_log"
      },
      "minRolls": 1,
      "maxRolls": 4
    },
    {
      "chance": 1.0,
      "output": {
        "item": "atmospheric:kousa_leaves"
      },
      "minRolls": 2,
      "maxRolls": 4
    },
    {
      "chance": 0.15,
      "output": {
        "item": "atmospheric:kousa_sapling"
      },
      "minRolls": 1,
      "maxRolls": 2
    },
    {
      "chance": 0.05,
      "output": {
        "item": "minecraft:stick"
      },
      "minRolls": 1,
      "maxRolls": 2
    }
  ]
}
